Homework_1/src/palindrome_synch_ckt.vhd
library IEEE;
use IEEE.STD_LOGIC_1164.ALL;
use IEEE.NUMERIC_STD.ALL;

entity palindrome_synch_ckt is
  generic(n : natural := 5);
  port(
    x, y, ck, reset : in  std_logic;
    z               : out std_logic
  );
end entity palindrome_synch_ckt;

architecture rtl of palindrome_synch_ckt is
  signal x_shift : std_logic_vector(n - 1 downto 0) := (others => '0');
  signal y_shift : std_logic_vector(n - 1 downto 0) := (others => '0');
  signal count   : natural range 0 to n := 0;
  signal z_reg   : std_logic := '0';

  function reverse_bits(v : std_logic_vector) return std_logic_vector is
    variable r : std_logic_vector(v'range);
  begin
    for i in 0 to v'length - 1 loop
      r(i) := v(v'length - 1 - i);
    end loop;
    return r;
  end function;
begin
  z <= z_reg;

  process(ck)
    variable x_next : std_logic_vector(n - 1 downto 0);
    variable y_next : std_logic_vector(n - 1 downto 0);
  begin
    if rising_edge(ck) then
      if reset = '1' then
        x_shift <= (others => '0');
        y_shift <= (others => '0');
        count   <= 0;
        z_reg   <= '0';
      else
        if count < n then
          x_next := x_shift(n - 2 downto 0) & x;
          y_next := y_shift(n - 2 downto 0) & y;

          x_shift <= x_next;
          y_shift <= y_next;
          count   <= count + 1;

          -- Evaluate exactly after the n-th sample is captured.
          if count = n - 1 then
            if x_next = reverse_bits(y_next) then
              z_reg <= '1';
            else
              z_reg <= '0';
            end if;
          end if;
        else
          if x_shift = reverse_bits(y_shift) then
            z_reg <= '1';
          else
            z_reg <= '0';
          end if;
        end if;
      end if;
    end if;
  end process;
end architecture rtl;

Homework_1/tb/tb_palindrome_synch_ckt.vhd
library IEEE;
use IEEE.STD_LOGIC_1164.ALL;
use std.env.all;

entity tb_palindrome_synch_ckt is
end entity tb_palindrome_synch_ckt;

architecture sim of tb_palindrome_synch_ckt is
  constant n_c : natural := 5;
  signal x     : std_logic := '0';
  signal y     : std_logic := '0';
  signal ck    : std_logic := '0';
  signal reset : std_logic := '1';
  signal z     : std_logic;

  constant Tck : time := 10 ns;
begin
  dut : entity work.palindrome_synch_ckt
    generic map(n => n_c)
    port map(
      x => x,
      y => y,
      ck => ck,
      reset => reset,
      z => z
    );

  ck <= not ck after Tck / 2;

  stim : process
    -- Test 1: x sequence 1,0,1,0,1 and y sequence 1,0,1,0,1
    -- reverse(y) = 1,0,1,0,1 -> palindrome match -> z = 1
    type bit_array_t is array (0 to n_c - 1) of std_logic;
    constant x_seq_match : bit_array_t := ('1', '0', '1', '0', '1');
    constant y_seq_match : bit_array_t := ('1', '0', '1', '0', '1');

    -- Test 2: x sequence 1,1,0,0,1 and y sequence 1,0,1,0,0
    -- reverse(y) = 0,0,1,0,1 /= x -> no match -> z = 0
    constant x_seq_miss : bit_array_t := ('1', '1', '0', '0', '1');
    constant y_seq_miss : bit_array_t := ('1', '0', '1', '0', '0');
  begin
    reset <= '1';
    wait for 2 * Tck;
    reset <= '0';

    for i in 0 to n_c - 1 loop
      x <= x_seq_match(i);
      y <= y_seq_match(i);
      wait until rising_edge(ck);
    end loop;

    wait until rising_edge(ck);
    assert z = '1'
      report "Palindrome test 1 failed (expected z=1)"
      severity error;

    reset <= '1';
    wait until rising_edge(ck);
    reset <= '0';

    for i in 0 to n_c - 1 loop
      x <= x_seq_miss(i);
      y <= y_seq_miss(i);
      wait until rising_edge(ck);
    end loop;

    wait until rising_edge(ck);
    assert z = '0'
      report "Palindrome test 2 failed (expected z=0)"
      severity error;

    report "tb_palindrome_synch_ckt PASSED" severity note;
    stop;
    wait;
  end process;
end architecture sim;

Homework_1/artifacts/sim/waves_palindrome.vcd
$date
   Wed Apr  8 01:42:48 2026
$end

$version
  2025.2
$end

$timescale
  1ps
$end

$scope module tb_palindrome_synch_ckt $end
$var wire 1 ! x $end
$var wire 1 " y $end
$var wire 1 # ck $end
$var wire 1 $ reset $end
$var wire 1 % z $end
$scope module dut $end
$var wire 1 ! x $end
$var wire 1 " y $end
$var wire 1 # ck $end
$var wire 1 $ reset $end
$var wire 1 % z $end
$var wire 5 & x_shift $end
$var wire 5 ' y_shift $end
$var wire 1 ( z_reg $end
$scope task line__30 $end
$upscope $end
$upscope $end
$scope task stim $end
$upscope $end
$upscope $end
$enddefinitions $end

#0
$dumpvars
0!
0"
0#
1$
0%
b0 &
b0 '
0(
$end

#5000
1#

#10000
0#

#15000
1#

#20000
1!
1"
0#
0$

#25000
0!
0"
1#
b1 &
b1 '

#30000
0#

#35000
1!
1"
1#
b10 &
b10 '

#40000
0#

#45000
0!
0"
1#
b101 &
b101 '

#50000
0#

#55000
1!
1"
1#
b1010 &
b1010 '

#60000
0#

#65000
1#
1%
b10101 &
b10101 '
1(

#70000
0#

#75000
1#
1$

#80000
0#

#85000
1!
1"
1#
0$
0%
b0 &
b0 '
0(

#90000
0#

#95000
1!
0"
1#
b1 &
b1 '

#100000
0#

#105000
0!
1"
1#
b11 &
b10 '

#110000
0#

#115000
0!
0"
1#
b110 &
b101 '

#120000
0#

#125000
1!
0"
1#
b1100 &
b1010 '

#130000
0#

#135000
1#
b11001 &
b10100 '

