Homework_1/src/output_limiter.vhd
library IEEE;
use IEEE.STD_LOGIC_1164.ALL;

package output_limiter is
  constant n : natural := 4;
end package output_limiter;

library IEEE;
use IEEE.STD_LOGIC_1164.ALL;
use IEEE.NUMERIC_STD.ALL;
use work.output_limiter.all;

entity user_logic is
  generic(
    u : std_logic_vector(n - 1 downto 0) := (others => '1');
    l : std_logic_vector(n - 1 downto 0) := (others => '0')
  );
  port(
    x : in  std_logic_vector(n - 1 downto 0);
    z : out std_logic_vector(n - 1 downto 0)
  );
end entity user_logic;

architecture rtl of user_logic is
begin
  process(x)
  begin
    if unsigned(x) < unsigned(l) then
      z <= l;
    elsif unsigned(x) > unsigned(u) then
      z <= u;
    else
      z <= x;
    end if;
  end process;
end architecture rtl;

Homework_1/tb/tb_output_limiter.vhd
library IEEE;
use IEEE.STD_LOGIC_1164.ALL;
use IEEE.NUMERIC_STD.ALL;
use std.env.all;
use work.output_limiter.all;

entity tb_output_limiter is
end entity tb_output_limiter;

architecture sim of tb_output_limiter is
  signal x : std_logic_vector(n - 1 downto 0) := (others => '0');
  signal z : std_logic_vector(n - 1 downto 0);
begin
  dut : entity work.user_logic
    generic map(
      u => "1010", -- 10
      l => "0101"  -- 5
    )
    port map(
      x => x,
      z => z
    );

  stim : process
    variable expected : unsigned(n - 1 downto 0);
  begin
    for i in 0 to (2 ** n) - 1 loop
      x <= std_logic_vector(to_unsigned(i, n));
      wait for 10 ns;

      if i < 5 then
        expected := to_unsigned(5, n);
      elsif i > 10 then
        expected := to_unsigned(10, n);
      else
        expected := to_unsigned(i, n);
      end if;

      assert unsigned(z) = expected
        report "Limiter mismatch at x=" & integer'image(i)
        severity error;
    end loop;

    report "tb_output_limiter PASSED" severity note;
    stop;
    wait;
  end process;
end architecture sim;

Homework_1/artifacts/sim/waves_limiter.vcd
$date
   Wed Apr  8 01:42:45 2026
$end

$version
  2025.2
$end

$timescale
  1ps
$end

$scope module tb_output_limiter $end
$var wire 4 ! x $end
$var wire 4 " z $end
$scope module dut $end
$var wire 4 ! x $end
$var wire 4 " z $end
$upscope $end
$scope task stim $end
$upscope $end
$upscope $end
$scope module output_limiter $end
$upscope $end
$enddefinitions $end

#0
$dumpvars
b0 !
b101 "
$end

#10000
b1 !

#20000
b10 !

#30000
b11 !

#40000
b100 !

#50000
b101 !

#60000
b110 !
b110 "

#70000
b111 !
b111 "

#80000
b1000 !
b1000 "

#90000
b1001 !
b1001 "

#100000
b1010 !
b1010 "

#110000
b1011 !

#120000
b1100 !

#130000
b1101 !

#140000
b1110 !

#150000
b1111 !
