Homework_1/src/c_accum_0.vhd
library IEEE;
use IEEE.STD_LOGIC_1164.ALL;
use IEEE.NUMERIC_STD.ALL;

-- Behavioral stand-in for Vivado C_ACCUM IP (4-bit signed in, 8-bit signed out).
entity c_accum_0 is
  port(
    B    : in  std_logic_vector(3 downto 0);
    CLK  : in  std_logic;
    SCLR : in  std_logic;
    Q    : out std_logic_vector(7 downto 0)
  );
end entity c_accum_0;

architecture rtl of c_accum_0 is
  signal acc : signed(7 downto 0) := (others => '0');
begin
  process(CLK)
  begin
    if rising_edge(CLK) then
      if SCLR = '1' then
        acc <= (others => '0');
      else
        acc <= acc + resize(signed(B), 8);
      end if;
    end if;
  end process;

  Q <= std_logic_vector(acc);
end architecture rtl;

Homework_1/src/accumulator_top.vhd
library IEEE;
use IEEE.STD_LOGIC_1164.ALL;

entity accumulator_top is
  port(
    ck    : in  std_logic;
    sclr  : in  std_logic;
    x     : in  std_logic_vector(3 downto 0);
    q     : out std_logic_vector(7 downto 0)
  );
end entity accumulator_top;

architecture rtl of accumulator_top is
begin
  u_ip : entity work.c_accum_0
    port map(
      B    => x,
      CLK  => ck,
      SCLR => sclr,
      Q    => q
    );
end architecture rtl;

Homework_1/tb/tb_accumulator_top.vhd
library IEEE;
use IEEE.STD_LOGIC_1164.ALL;
use IEEE.NUMERIC_STD.ALL;
use std.env.all;

entity tb_accumulator_top is
end entity tb_accumulator_top;

architecture sim of tb_accumulator_top is
  signal ck   : std_logic := '0';
  signal sclr : std_logic := '0';
  signal x    : std_logic_vector(3 downto 0) := (others => '0');
  signal q    : std_logic_vector(7 downto 0);

  constant Tck : time := 10 ns;

  type int_array_t is array (natural range <>) of integer;
  -- 20 signed 4-bit values in allowed range [-8..7]
  constant seq20 : int_array_t := (
    -8, -7, -6, -5, -4, -3, -2, -1, 0, 1,
     2,  3,  4,  5,  6,  7, -8,  7, -1, 6
  );
begin
  dut : entity work.accumulator_top
    port map(
      ck => ck,
      sclr => sclr,
      x => x,
      q => q
    );

  ck <= not ck after Tck / 2;

  stim : process
    variable expected_sum : integer := 0;
  begin
    sclr <= '1';
    wait until rising_edge(ck);
    wait for 1 ns;
    sclr <= '0';
    wait until rising_edge(ck);
    wait for 1 ns;
    assert signed(q) = to_signed(0, 8)
      report "Accumulator clear failed"
      severity error;

    for i in seq20'range loop
      x <= std_logic_vector(to_signed(seq20(i), 4));
      wait until rising_edge(ck);
      wait for 1 ns;

      expected_sum := expected_sum + seq20(i);
      assert signed(q) = to_signed(expected_sum, 8)
        report "Accumulator mismatch at sample " & integer'image(i)
        severity error;
    end loop;

    report "tb_accumulator_top PASSED" severity note;
    stop;
    wait;
  end process;
end architecture sim;

Homework_1/artifacts/sim/waves.vcd
$date
   Wed Apr  8 01:13:00 2026
$end

$version
  2025.2
$end

$timescale
  1ps
$end

$scope module tb_accumulator_top $end
$var wire 1 ! ck $end
$var wire 1 " sclr $end
$var wire 4 # x $end
$var wire 8 $ q $end
$scope module dut $end
$var wire 1 ! ck $end
$var wire 1 " sclr $end
$var wire 4 # x $end
$var wire 8 $ q $end
$scope module u_ip $end
$var wire 4 # B $end
$var wire 1 ! CLK $end
$var wire 1 " SCLR $end
$var wire 8 $ Q $end
$var wire 8 % acc $end
$upscope $end
$upscope $end
$scope task stim $end
$upscope $end
$upscope $end
$enddefinitions $end

#0
$dumpvars
0!
1"
b0 #
b0 $
b0 %
$end

#5000
1!

#6000
0"

#10000
0!

#15000
1!

#16000
b1000 #

#20000
0!

#25000
1!
b11111000 $
b11111000 %

#26000
b1001 #

#30000
0!

#35000
1!
b11110001 $
b11110001 %

#36000
b1010 #

#40000
0!

#45000
1!
b11101011 $
b11101011 %

#46000
b1011 #

#50000
0!

#55000
1!
b11100110 $
b11100110 %

#56000
b1100 #

#60000
0!

#65000
1!
b11100010 $
b11100010 %

#66000
b1101 #

#70000
0!

#75000
1!
b11011111 $
b11011111 %

#76000
b1110 #

#80000
0!

#85000
1!
b11011101 $
b11011101 %

#86000
b1111 #

#90000
0!

#95000
1!
b11011100 $
b11011100 %

#96000
b0 #

#100000
0!

#105000
1!

#106000
b1 #

#110000
0!

#115000
1!
b11011101 $
b11011101 %

#116000
b10 #

#120000
0!

#125000
1!
b11011111 $
b11011111 %

#126000
b11 #

#130000
0!

#135000
1!
b11100010 $
b11100010 %

#136000
b100 #

#140000
0!

#145000
1!
b11100110 $
b11100110 %

#146000
b101 #

#150000
0!

#155000
1!
b11101011 $
b11101011 %

#156000
b110 #

#160000
0!

#165000
1!
b11110001 $
b11110001 %

#166000
b111 #

#170000
0!

#175000
1!
b11111000 $
b11111000 %

#176000
b1000 #

#180000
0!

#185000
1!
b11110000 $
b11110000 %

#186000
b111 #

#190000
0!

#195000
1!
b11110111 $
b11110111 %

#196000
b1111 #

#200000
0!

#205000
1!
b11110110 $
b11110110 %

#206000
b110 #

#210000
0!

#215000
1!
b11111100 $
b11111100 %
